[
    {
        "generator_version": "UAV2_gen12"
    },
    {
        "name": "design_12028_e437c0c4835841a99d48808aa8734bc7_s"
    },
    {
        "node_type": "ConnectedHub4_Sym"
    },
    {
        "node_type": "PropArm"
    },
    {
        "armLength": 413.5996130739701
    },
    {
        "motorType": "t_motor_AT3530KV580"
    },
    {
        "propType": "apc_propellers_18x8"
    },
    {
        "offset": 41.65045980035022
    },
    {
        "angle": 0.0
    },
    {
        "node_type": "SingleBatteryFuselageWithComponents"
    },
    {
        "batteryType": "TurnigyGraphene2200mAh3S75C"
    },
    {
        "length": 106.0
    },
    {
        "vertDiameter": 52.5
    },
    {
        "horzDiameter": 332.4
    },
    {
        "floorHeight": 8.75
    },
    {
        "batteryX": 0.0
    },
    {
        "batteryY": 6.0
    },
    {
        "rpmX": 0.0
    },
    {
        "rpmY": -100.8
    },
    {
        "autoPilotX": 0.0
    },
    {
        "autoPilotY": 44.5
    },
    {
        "currentX": 0.0
    },
    {
        "currentY": -80.65
    },
    {
        "voltageX": 0.0
    },
    {
        "voltageY": 98.3
    },
    {
        "gpsX": 0.0
    },
    {
        "gpsY": -40.5
    },
    {
        "varioX": 0.0
    },
    {
        "varioY": 76.65
    }
]